simplesuper.py
simplesuper-1.0.10.dist-info/LICENSE.txt
simplesuper-1.0.10.dist-info/METADATA
simplesuper-1.0.10.dist-info/WHEEL
simplesuper-1.0.10.dist-info/top_level.txt
simplesuper-1.0.10.dist-info/RECORD
