Metadata-Version: 2.1
Name: simplesuper
Version: 1.0.10
Summary: Simpler way to call super methods without all the repetition
Home-page: https://github.com/dwt/simplesuper
Author: Martin Häcker, Robert Buchholz, Felix Schwarz
Author-email: mhaecker@mac.com, rbu@rbu.sh, felix@schwarz-online.org
License: ISC
Keywords: python 2,super,convenience,api
Classifier: Programming Language :: Python :: 2
Classifier: Topic :: Software Development
Classifier: Topic :: Utilities
Classifier: Intended Audience :: Developers
Classifier: Development Status :: 5 - Production/Stable
Classifier: License :: OSI Approved :: ISC License (ISCL)
License-File: LICENSE.txt
